staros/__init__.py
staros/additionalparse.py
staros/connection.py
staros/core.py
staros/outputparsing.py
staros/params.py
staros/subscriber.py
staros/test.py
staros/test1.py
staros/test2.py
staros-0.6.dist-info/DESCRIPTION.rst
staros-0.6.dist-info/METADATA
staros-0.6.dist-info/RECORD
staros-0.6.dist-info/WHEEL
staros-0.6.dist-info/metadata.json
staros-0.6.dist-info/top_level.txt
