Metadata-Version: 2.0
Name: staros
Version: 0.6
Summary: Module for comunicate with staros device
Home-page: UNKNOWN
Author: Dzmitry Buynovskiy
Author-email: imperituro@mail.com
License: MIT
Keywords: staros ASR ASR5700 ASR5000
Platform: UNKNOWN
Classifier: Development Status :: 3 - Alpha
Classifier: License :: OSI Approved :: MIT License
Classifier: Programming Language :: Python :: 2.7
Classifier: Topic :: Text Processing :: Linguistic
Requires-Dist: paramiko
